[
    {
        "name": "Something bad happened",
        "description": "Something bad happened in this sample event",
        "isCrisis": true,
        "choices": [
            {
                "description": "Use medical department",
                "targetTrigram": "MED",
                "cost": 2,
                "effects": [
                    {
                        "methodName": "",
                        "arguments": ""
                    }
                ],
                "requirements": {
                    "MED_SUR": 5
                }
            },
            {
                "description": "Use engineering department",
                "targetTrigram": "ENG",
                "cost": 3,
                "effects": []
            }
        ]
    }
]